showroompodcast/__init__.py
showroompodcast/archiving_task_manager.py
showroompodcast/cli.py
showroompodcast/config.py
showroompodcast/exceptions.py
showroompodcast/py.typed
showroompodcast/raise_if.py
showroompodcast/showroom_archiver.py
showroompodcast/showroom_datetime.py
showroompodcast/showroom_podcast.py
showroompodcast/showroom_poller.py
showroompodcast/showroom_stream_spec_factory.py
showroompodcast/api/__init__.py
showroompodcast/api/polling.py
showroompodcast/api/streaming_url.py
showroompodcast/slack/__init__.py
showroompodcast/slack/slack_client.py
showroompodcast-20241231044500.dist-info/LICENSE
showroompodcast-20241231044500.dist-info/METADATA
showroompodcast-20241231044500.dist-info/WHEEL
showroompodcast-20241231044500.dist-info/entry_points.txt
showroompodcast-20241231044500.dist-info/top_level.txt
showroompodcast-20241231044500.dist-info/RECORD
