Metadata-Version: 2.1
Name: showroompodcast
Version: 20241231044500
Summary: Automatic archiver for SHOWROOM live which is listed by YAML file.
Author-email: Master <roadmasternavi@gmail.com>
Maintainer-email: Master <roadmasternavi@gmail.com>
License: MIT License
Project-URL: homepage, https://github.com/road-master/showroom-podcast
Project-URL: repository, https://github.com/road-master/showroom-podcast
Keywords: archive,showroom
Classifier: Development Status :: 5 - Production/Stable
Classifier: Intended Audience :: End Users/Desktop
Classifier: License :: OSI Approved :: MIT License
Classifier: Natural Language :: English
Classifier: Operating System :: OS Independent
Classifier: Programming Language :: Python
Classifier: Programming Language :: Python :: 3
Classifier: Programming Language :: Python :: 3.9
Classifier: Topic :: Internet :: WWW/HTTP
Classifier: Topic :: Internet :: WWW/HTTP :: Dynamic Content
Classifier: Topic :: Internet :: WWW/HTTP :: Dynamic Content :: Content Management System
Classifier: Topic :: Multimedia
Classifier: Topic :: Multimedia :: Video
Classifier: Topic :: Multimedia :: Video :: Capture
Classifier: Topic :: System
Classifier: Topic :: System :: Archiving
Classifier: Topic :: System :: Archiving :: Backup
Classifier: Topic :: System :: Monitoring
Classifier: Topic :: System :: Networking
Classifier: Topic :: System :: Networking :: Monitoring
Classifier: Typing :: Typed
Requires-Python: >=3.9
License-File: LICENSE
Requires-Dist: asynccpu
Requires-Dist: asyncffmpeg
Requires-Dist: click>=7.0
Requires-Dist: requests
Requires-Dist: slack-sdk
Requires-Dist: yamldataclassconfig
Provides-Extra: test
